grlib/__init__.py
grlib/dynamic_detector.py
grlib/exceptions.py
grlib/data_augmentation/__init__.py
grlib/data_augmentation/common.py
grlib/data_augmentation/landmarks_2d.py
grlib/feature_extraction/__init__.py
grlib/feature_extraction/mediapipe_landmarks.py
grlib/feature_extraction/pipeline.py
grlib/feature_extraction/stage.py
grlib/filter/__init__.py
grlib/filter/false_positive_filter.py
grlib/load_data/__init__.py
grlib/load_data/base_loader.py
grlib/load_data/by_folder_loader.py
grlib/load_data/dynamic_gesture_loader.py
grlib/load_data/with_labels_loader.py
grlib/preprocessing/__init__.py
grlib/preprocessing/all_landmarks.py
grlib/preprocessing/images.py
grlib/preprocessing/spacial_landmarks.py
grlib/rotation_invariance/__init__.py
grlib/rotation_invariance/icp.py
grlib/rotation_invariance/transform.py
grlib/trajectory/__init__.py
grlib/trajectory/general_direction_builder.py
grlib/trajectory/key_frames.py
grlib/trajectory/trajectory_candidate.py
grlib/trajectory/trajectory_classifier.py
grlib-1.0.12.dist-info/METADATA
grlib-1.0.12.dist-info/WHEEL
grlib-1.0.12.dist-info/top_level.txt
grlib-1.0.12.dist-info/RECORD
