Metadata-Version: 2.1
Name: grlib
Version: 1.0.12
Summary: Gesture recognition library for Python
Author-email: Jan Warchocki <j.warchocki@student.tudelft.nl>, Mikhail Vlasenko <m.vlasenko@student.tudelft.nl>
Project-URL: Homepage, https://github.com/mikhail-vlasenko/grlib
Classifier: Programming Language :: Python
Classifier: Programming Language :: Python :: 3
Requires-Python: >=3.8
Requires-Dist: numpy ~=1.21.4
Requires-Dist: pandas ~=1.3.4
Requires-Dist: mediapipe ~=0.8.9
Requires-Dist: scikit-learn ~=1.2.2
Requires-Dist: opencv-contrib-python ~=4.5.4.50
Requires-Dist: imutils ~=0.5.4
Requires-Dist: natsort ~=8.3.1
